requirements.txt
setup.py
requests_retry_on_exceptions/__init__.py
requests_retry_on_exceptions.egg-info/PKG-INFO
requests_retry_on_exceptions.egg-info/SOURCES.txt
requests_retry_on_exceptions.egg-info/dependency_links.txt
requests_retry_on_exceptions.egg-info/requires.txt
requests_retry_on_exceptions.egg-info/top_level.txt