Metadata-Version: 2.1
Name: requests-retry-on-exceptions
Version: 2020.7.2
Summary: requests retry on exceptions
Home-page: https://github.com/andrewp-as-is/requests-retry-on-exceptions.py
License: Unlicense
Keywords: requests retry
Platform: UNKNOWN
Classifier: License :: Public Domain
Classifier: Operating System :: OS Independent
Classifier: Programming Language :: Python :: 3
